<?xml version="1.0" encoding="UTF-8"?>
<objects serializationModel="Studio.02.01.00">
	<object class="MixerGroup" id="{30a3b975-2f4a-47f6-b0c2-34029ec46851}">
		<property name="color">
			<value>Yellow</value>
		</property>
		<property name="name">
			<value>Objects</value>
		</property>
		<relationship name="effectChain">
			<destination>{5910500c-4603-4247-a5fa-bb9bb79b0745}</destination>
		</relationship>
		<relationship name="panner">
			<destination>{c5de7316-fa4c-4224-962e-ac3ed5ce96a6}</destination>
		</relationship>
		<relationship name="output">
			<destination>{0d701ae7-c4e0-424c-aa96-fccddccd5f44}</destination>
		</relationship>
	</object>
	<object class="MixerBusEffectChain" id="{5910500c-4603-4247-a5fa-bb9bb79b0745}">
		<relationship name="effects">
			<destination>{392dcd0f-1d84-4ecf-97c8-b55ac12a9b7a}</destination>
			<destination>{619f9f53-9985-44e2-accd-9e41f96e2e52}</destination>
		</relationship>
	</object>
	<object class="MixerBusPanner" id="{c5de7316-fa4c-4224-962e-ac3ed5ce96a6}" />
	<object class="MixerSend" id="{392dcd0f-1d84-4ecf-97c8-b55ac12a9b7a}">
		<property name="inputFormat">
			<value>0</value>
		</property>
		<relationship name="mixerReturn">
			<destination>{034181ee-dfd5-436d-bd1e-918594ce683a}</destination>
		</relationship>
	</object>
	<object class="MixerBusFader" id="{619f9f53-9985-44e2-accd-9e41f96e2e52}" />
</objects>
